{"intents": [
        {"tag": "greeting",
         "patterns": ["Hi", "How are you", "Is anyone there?", "Hello", "Good day"],
         "responses": ["Hello, thanks for visiting", "Good to see you again", "Hi there, how can I help?"],
         "context_set": ""
        },
        {"tag": "goodbye",
         "patterns": ["Bye", "See you later", "Goodbye"],
         "responses": ["See you later, thanks for visiting", "Have a nice day", "Bye! Come back again soon."]
        },
        {"tag": "app",
         "patterns": ["What is this app about?","What about this app?","App?"],
         "responses": ["This is a download scheduler","You can use to download items"]
        },
        {"tag": "versions",
         "patterns": ["What are the supported file formats?", "Formats?", "File types?" ],
         "responses": ["Youtube vides,Pdf,Mp3", "Mp4,Mp3,PDF"]
        },
        {"tag": "thanks",
         "patterns": ["Thanks", "Thank you", "That's helpful"],
         "responses": ["Happy to help!", "Any time!", "My pleasure"]
        }
   ]
}
